Classfile /C:/Users/Administrator/Desktop/²©¿Í/jvm/Test.class
  Last modified 2018-6-26; size 1513 bytes
  MD5 checksum ea05552b67933634329b70d28e818cb5
  Compiled from "Test.java"
public class com.test.Test
  minor version: 0
  major version: 52
  flags: ACC_PUBLIC, ACC_SUPER
Constant pool:
   #1 = Class              #2             // com/test/Test
   #2 = Utf8               com/test/Test
   #3 = Class              #4             // java/lang/Object
   #4 = Utf8               java/lang/Object
   #5 = Utf8               <init>
   #6 = Utf8               ()V
   #7 = Utf8               Code
   #8 = Methodref          #3.#9          // java/lang/Object."<init>":()V
   #9 = NameAndType        #5:#6          // "<init>":()V
  #10 = Utf8               LineNumberTable
  #11 = Utf8               LocalVariableTable
  #12 = Utf8               this
  #13 = Utf8               Lcom/test/Test;
  #14 = Utf8               main
  #15 = Utf8               ([Ljava/lang/String;)V
  #16 = Class              #17            // com/test/Test$1
  #17 = Utf8               com/test/Test$1
  #18 = Methodref          #16.#9         // com/test/Test$1."<init>":()V
  #19 = String             #20            //
  #20 = Utf8
  #21 = InterfaceMethodref #22.#24        // com/test/ICommonView.getData:(Ljava/lang/Object;)V
  #22 = Class              #23            // com/test/ICommonView
  #23 = Utf8               com/test/ICommonView
  #24 = NameAndType        #25:#26        // getData:(Ljava/lang/Object;)V
  #25 = Utf8               getData
  #26 = Utf8               (Ljava/lang/Object;)V
  #27 = Class              #28            // com/test/Teacher
  #28 = Utf8               com/test/Teacher
  #29 = Methodref          #27.#9         // com/test/Teacher."<init>":()V
  #30 = InterfaceMethodref #22.#31        // com/test/ICommonView.getData2:(Ljava/lang/Object;)V
  #31 = NameAndType        #32:#26        // getData2:(Ljava/lang/Object;)V
  #32 = Utf8               getData2
  #33 = Fieldref           #34.#36        // java/lang/System.out:Ljava/io/PrintStream;
  #34 = Class              #35            // java/lang/System
  #35 = Utf8               java/lang/System
  #36 = NameAndType        #37:#38        // out:Ljava/io/PrintStream;
  #37 = Utf8               out
  #38 = Utf8               Ljava/io/PrintStream;
  #39 = Methodref          #1.#40         // com/test/Test.getDaysByYearMonth:(II)I
  #40 = NameAndType        #41:#42        // getDaysByYearMonth:(II)I
  #41 = Utf8               getDaysByYearMonth
  #42 = Utf8               (II)I
  #43 = Methodref          #44.#46        // java/io/PrintStream.println:(I)V
  #44 = Class              #45            // java/io/PrintStream
  #45 = Utf8               java/io/PrintStream
  #46 = NameAndType        #47:#48        // println:(I)V
  #47 = Utf8               println
  #48 = Utf8               (I)V
  #49 = Utf8               args
  #50 = Utf8               [Ljava/lang/String;
  #51 = Utf8               commonView
  #52 = Utf8               Lcom/test/ICommonView;
  #53 = Utf8               i
  #54 = Utf8               I
  #55 = Utf8               StackMapTable
  #56 = Utf8               initTime
  #57 = String             #58            // 2
  #58 = Utf8               2
  #59 = Utf8               timeMode
  #60 = Utf8               start24Hour
  #61 = Utf8               Ljava/lang/String;
  #62 = Utf8               start24Min
  #63 = Utf8               end24Hour
  #64 = Utf8               end24Min
  #65 = Class              #66            // java/lang/String
  #66 = Utf8               java/lang/String
  #67 = Methodref          #68.#70        // java/util/Calendar.getInstance:()Ljava/util/Calendar;
  #68 = Class              #69            // java/util/Calendar
  #69 = Utf8               java/util/Calendar
  #70 = NameAndType        #71:#72        // getInstance:()Ljava/util/Calendar;
  #71 = Utf8               getInstance
  #72 = Utf8               ()Ljava/util/Calendar;
  #73 = Methodref          #68.#74        // java/util/Calendar.set:(II)V
  #74 = NameAndType        #75:#76        // set:(II)V
  #75 = Utf8               set
  #76 = Utf8               (II)V
  #77 = Methodref          #68.#78        // java/util/Calendar.roll:(II)V
  #78 = NameAndType        #79:#76        // roll:(II)V
  #79 = Utf8               roll
  #80 = Methodref          #68.#81        // java/util/Calendar.get:(I)I
  #81 = NameAndType        #82:#83        // get:(I)I
  #82 = Utf8               get
  #83 = Utf8               (I)I
  #84 = Utf8               year
  #85 = Utf8               month
  #86 = Utf8               a
  #87 = Utf8               Ljava/util/Calendar;
  #88 = Utf8               maxDate
  #89 = Utf8               SourceFile
  #90 = Utf8               Test.java
  #91 = Utf8               InnerClasses
{
  public com.test.Test();
    descriptor: ()V
    flags: ACC_PUBLIC
    Code:
      stack=1, locals=1, args_size=1
         0: aload_0
         1: invokespecial #8                  // Method java/lang/Object."<init>":()V
         4: return
      LineNumberTable:
        line 5: 0
      LocalVariableTable:
        Start  Length  Slot  Name   Signature
            0       5     0  this   Lcom/test/Test;

  public static void main(java.lang.String[]);
    descriptor: ([Ljava/lang/String;)V
    flags: ACC_PUBLIC, ACC_STATIC
    Code:
      stack=3, locals=3, args_size=1
         0: new           #16                 // class com/test/Test$1
         3: dup
         4: invokespecial #18                 // Method com/test/Test$1."<init>":()V
         7: astore_1
         8: aload_1
         9: ldc           #19                 // String
        11: invokeinterface #21,  2           // InterfaceMethod com/test/ICommonView.getData:(Ljava/lang/Object;)V
        16: aload_1
        17: new           #27                 // class com/test/Teacher
        20: dup
        21: invokespecial #29                 // Method com/test/Teacher."<init>":()V
        24: invokeinterface #30,  2           // InterfaceMethod com/test/ICommonView.getData2:(Ljava/lang/Object;)V
        29: iconst_1
        30: istore_2
        31: goto          50
        34: getstatic     #33                 // Field java/lang/System.out:Ljava/io/PrintStream;
        37: sipush        2016
        40: iload_2
        41: invokestatic  #39                 // Method getDaysByYearMonth:(II)I
        44: invokevirtual #43                 // Method java/io/PrintStream.println:(I)V
        47: iinc          2, 1
        50: iload_2
        51: bipush        12
        53: if_icmple     34
        56: return
      LineNumberTable:
        line 7: 0
        line 21: 8
        line 22: 16
        line 23: 29
        line 24: 34
        line 23: 47
        line 26: 56
      LocalVariableTable:
        Start  Length  Slot  Name   Signature
            0      57     0  args   [Ljava/lang/String;
            8      49     1 commonView   Lcom/test/ICommonView;
           31      25     2     i   I
      StackMapTable: number_of_entries = 2
        frame_type = 253 /* append */
          offset_delta = 34
          locals = [ class com/test/ICommonView, int ]
        frame_type = 15 /* same */

  public static void initTime();
    descriptor: ()V
    flags: ACC_PUBLIC, ACC_STATIC
    Code:
      stack=2, locals=5, args_size=0
         0: iconst_1
         1: istore_0
         2: ldc           #57                 // String 2
         4: astore_1
         5: ldc           #57                 // String 2
         7: astore_2
         8: ldc           #57                 // String 2
        10: astore_3
        11: ldc           #57                 // String 2
        13: astore        4
        15: iload_0
        16: iconst_1
        17: if_icmpeq     20
        20: return
      LineNumberTable:
        line 33: 0
        line 34: 2
        line 35: 5
        line 36: 8
        line 37: 11
        line 39: 15
        line 53: 20
      LocalVariableTable:
        Start  Length  Slot  Name   Signature
            2      19     0 timeMode   I
            5      16     1 start24Hour   Ljava/lang/String;
            8      13     2 start24Min   Ljava/lang/String;
           11      10     3 end24Hour   Ljava/lang/String;
           15       6     4 end24Min   Ljava/lang/String;
      StackMapTable: number_of_entries = 1
        frame_type = 255 /* full_frame */
          offset_delta = 20
          locals = [ int, class java/lang/String, class java/lang/String, class java/lang/String, class java/lang/String ]
          stack = []

  public static int getDaysByYearMonth(int, int);
    descriptor: (II)I
    flags: ACC_PUBLIC, ACC_STATIC
    Code:
      stack=4, locals=4, args_size=2
         0: invokestatic  #67                 // Method java/util/Calendar.getInstance:()Ljava/util/Calendar;
         3: astore_2
         4: aload_2
         5: iconst_1
         6: iload_0
         7: invokevirtual #73                 // Method java/util/Calendar.set:(II)V
        10: aload_2
        11: iconst_2
        12: iload_1
        13: iconst_1
        14: isub
        15: invokevirtual #73                 // Method java/util/Calendar.set:(II)V
        18: aload_2
        19: iconst_5
        20: iconst_1
        21: invokevirtual #73                 // Method java/util/Calendar.set:(II)V
        24: aload_2
        25: iconst_5
        26: iconst_m1
        27: invokevirtual #77                 // Method java/util/Calendar.roll:(II)V
        30: aload_2
        31: iconst_5
        32: invokevirtual #80                 // Method java/util/Calendar.get:(I)I
        35: istore_3
        36: iload_3
        37: ireturn
      LineNumberTable:
        line 64: 0
        line 65: 4
        line 66: 10
        line 67: 18
        line 68: 24
        line 69: 30
        line 70: 36
      LocalVariableTable:
        Start  Length  Slot  Name   Signature
            0      38     0  year   I
            0      38     1 month   I
            4      34     2     a   Ljava/util/Calendar;
           36       2     3 maxDate   I
}
SourceFile: "Test.java"
InnerClasses:
     #16; //class com/test/Test$1
